{
  "created_at": "2020-07-12T11:02:22.000Z",
  "updated_at": "2021-01-06T08:25:00.110Z",
  "id": "c49a9927-f641-4893-97b5-c5d7da94f613",
  "labels": "current-affairs,2020-07-13",
  "question": "Which of the following sultan was the last sultan of Malwa?",
  "option1": "Baz Bahadur",
  "option2": "Mahmud Shah II",
  "option3": "Shujaat Khan",
  "option4": "Qadir Shah",
  "option5": "",
  "answer": "Baz Bahadur",
  "explanation": "After Sher Shah Suri conquered malwa from Qadir shah, he appointed Shujaat Khan as the governor. His son, Baz Bahadur, declared himself independent in 1555 CE. Baz Bahadur was the last sultan of Malwa."
}