{
  "created_at": "2019-02-09T01:17:50.000Z",
  "updated_at": "2021-01-06T08:24:36.633Z",
  "id": "be0b376f-4d74-4034-a3bd-489d33b54ddb",
  "labels": "current-affairs,2019-02-10",
  "question": "Which of the following methods is used to purify Titanium metal?",
  "option1": "Hall-Heroult process",
  "option2": "van Arkel method",
  "option3": "Mond process",
  "option4": "None of the above",
  "option5": "",
  "answer": "van Arkel method",
  "explanation": "van Arkel method is used for refining Titanium: This method is very useful for removing all the oxygen and nitrogen present in the form of impurity in Titanium."
}