{
  "created_at": "2019-03-01T19:23:27.000Z",
  "updated_at": "2021-01-06T08:24:37.407Z",
  "id": "2792be97-fb61-4aca-9b8f-1ef673df581d",
  "labels": "current-affairs,2019-03-02",
  "question": "Who developed the Arsphenamine medicine?",
  "option1": "Alexander Fleming",
  "option2": "Sahachiro Hata",
  "option3": "Marie curie",
  "option4": "Paul Ehrlich",
  "option5": "",
  "answer": "Paul Ehrlich",
  "explanation": "Paul Ehrlich, a German bacteriologist, developed the medicine, arsphenamine, known as salvarsan. Paul Ehrlich got Nobel prize for Medicine in 1908 for this discovery. It was the first effective treatment discovered for syphilis."
}