{
  "created_at": "2020-12-20T05:08:44.000Z",
  "updated_at": "2021-01-06T08:25:13.847Z",
  "id": "2b20c724-510f-4d73-bbb7-1a000fe3c1c8",
  "labels": "current-affairs,2020-12-21",
  "question": "ASTRA Mk-I Missile, IMSAS and BOSS System, which were handed over to the Armed Forces, were developed by which organisation?",
  "option1": "DRDO",
  "option2": "OFB",
  "option3": "BEL",
  "option4": "HAL",
  "option5": "",
  "answer": "DRDO",
  "explanation": "Defence Minister Rajnath Singh handed over three indigenously developed systems developed by the Defence Research and Development Organisation (DRDO) laboratories, to Army, Navy and Air Force. \r\nIndian Maritime Situational Awareness System (IMSAS) was handed over to the Navy, ASTRA Mk-I Missile to the Air Force and Border Surveillance System (BOSS) to the Army, which was already deployed in in Ladakh."
}