{
  "created_at": "2020-07-25T18:32:03.000Z",
  "updated_at": "2021-01-06T08:25:02.082Z",
  "id": "f28e6dc2-d3c6-4293-b606-81e242eab7aa",
  "labels": "current-affairs,2020-07-26",
  "question": "National Highways Authority of India( NHAI) approved the construction of India's first 4-level transit intersection in which of the following places?",
  "option1": "Mumbai",
  "option2": "Nagpur",
  "option3": "Kanpur",
  "option4": "Lucknow",
  "option5": "",
  "answer": "Nagpur",
  "explanation": "National Highways Authority of India( NHAI) approved the construction of India's first 4-level transit intersection in Nagpur, Maharashtra. A total of Rs 573 crores has been approved for this project."
}