{
  "created_at": "2020-07-29T20:44:03.000Z",
  "updated_at": "2021-01-06T08:25:04.832Z",
  "id": "a3e9e51c-bff3-4697-97b6-4b8d87b69ba7",
  "labels": "current-affairs,2020-07-30",
  "question": "Whcih of the following were the patrons of the Company style of art?<br />1) Lord Impey<br />2) Lord Wellesley<br />Select the correct answer from the codes given below:",
  "option1": "Only 1",
  "option2": "Only 2",
  "option3": "Both 1 & 2",
  "option4": "Neither 1 & 2",
  "option5": "",
  "answer": "Both 1 & 2",
  "explanation": "The Company style is a hybrid Indo-European style of paintings. The main patrons of the Company art were Lord Impey who was the Chief justice of the High Court, and Lord Wellesley who was the then Governor-General."
}