{
  "created_at": "2019-01-25T20:59:30.000Z",
  "updated_at": "2021-01-06T08:24:35.506Z",
  "id": "1e974266-9acb-437f-9d3b-fb3ea18dec22",
  "labels": "current-affairs,2019-01-26",
  "question": "What is the branch of physics that deals with the concepts of heat and temperature and the inter-conversion of heat and other forms of energy is known as?",
  "option1": "Calorimetry",
  "option2": "Thermodynamics",
  "option3": "Thermostatics",
  "option4": "Electrostatics",
  "option5": "",
  "answer": "Thermodynamics",
  "explanation": "Thermodynamics is the branch of physics that deals with the concepts of heat and temperature and the inter-conversion of heat and other forms of energy."
}