{
  "created_at": "2020-06-05T12:43:11.000Z",
  "updated_at": "2021-01-06T08:24:55.918Z",
  "id": "87cf14ba-de47-4d21-a5c8-ff863b3020fa",
  "labels": "current-affairs,2020-06-06",
  "question": "With which country did NNITI Aayog sign Memorandum of Understanding for Urban rejuvenation mission?",
  "option1": "Australia",
  "option2": "USA",
  "option3": "UK",
  "option4": "Singapore",
  "option5": "",
  "answer": "Singapore",
  "explanation": "NITI Aayog, Government of India has entered into an MoU (Memorandum of Understanding) with Singapore Cooperation Enterprise, (SCE), an agency of the Government of the Republic of Singapore for taking up the second phase of Capacity Building Programme in the field of Urban Planning and Development. This will facilitate the urban rejuvenation mission."
}