{
  "created_at": "2018-01-18T17:53:50.000Z",
  "updated_at": "2021-01-06T08:24:15.848Z",
  "id": "2afcad7a-98af-4384-a85f-005750570580",
  "labels": "current-affairs,2018-01-19",
  "question": "Many market linked insurance products &amp; mutual funds available in the market provide the consumers, a guarantee of return on the basis of Highest NAV known as Net Asset Value. The net asset value is a measure of ?",
  "option1": "Value of the total assets",
  "option2": "Value of a particular share at a time",
  "option3": "Value of a assets less the value of liabilities.",
  "option4": "Value of a share in respect with the other shares",
  "option5": "",
  "answer": "Value of a assets less the value of liabilities.",
  "explanation": ""
}