{
  "created_at": "2021-03-04T02:45:53.000Z",
  "updated_at": "2021-03-04T02:45:53.000Z",
  "id": "c2fb8753-70fb-480b-88b3-833759388958",
  "labels": "current-affairs,2021-03-05",
  "question": "Which country administers the \"Sumatra Island\"?",
  "option1": "Philippines",
  "option2": "Vietnam",
  "option3": "Malaysia",
  "option4": "Indonesia",
  "option5": "",
  "answer": "Indonesia",
  "explanation": "Indonesia administers the \"Sumatra Island\". Sumatra is one of the Sunda Islands of western Indonesia. It is the largest island that is fully within Indonesian territory, as well as the sixth-largest island in the world.",
  "verified_at": ""
}