{
  "created_at": "2020-07-07T16:04:49.000Z",
  "updated_at": "2021-01-06T08:24:58.553Z",
  "id": "fa4fffe7-6d8d-4465-9bf5-1370b137c7f6",
  "labels": "current-affairs,2020-07-08",
  "question": "The local system of canal irrigation found in Parts of Himachal Pradesh over four hundred years ago is known as?</span>",
  "option1": "Baori",
  "option2": "Khadin",
  "option3": "Jhalara",
  "option4": "Kuhl",
  "option5": "",
  "answer": "Kuhl",
  "explanation": "Kuhl is a type of traditional irrigation system in Himachal Pradesh. They are surface channels diverting water from natural flowing streams (khuds). A typical community of kuhls services 6 to 30 farmers, irrigating an area of about 20 ha.</span>"
}