{
  "created_at": "2017-07-03T00:00:00.000Z",
  "updated_at": "2021-01-09T09:22:53.330Z",
  "id": "48ce165e-cdc7-4025-a4bf-47c2057cd957",
  "labels": "current-affairs,2017-07-03",
  "question": "Who has become the first female Chief Executive of Hong Kong?",
  "option1": "Woo Kwok Tsang",
  "option2": "Lili Voga",
  "option3": "Carrie Lam",
  "option4": "Chang Yuet-ngor",
  "option5": "",
  "answer": "Carrie Lam",
  "explanation": "Carrie Lam has become the first woman chief executive of Hong Kong on July 1, 2017 after winning the 2017 Chief Executive election. She is known as a tough and effective enforcer. The Chief Executive of Hong Kong (CE) is the highest office of the Hong Kong Special Administrative Region (HKSAR). She was previously the top deputy to Leung Chun-ying, the unpopular chief executive who chose not to seek a second term.",
  "verified_at": ""
}