{
  "created_at": "2019-09-21T21:20:17.000Z",
  "updated_at": "2021-01-06T08:24:43.083Z",
  "id": "9ffabe73-53a4-4f3e-900f-fdad58822cd9",
  "labels": "current-affairs,2019-09-22",
  "question": "Which state government has  decided to ban private practice of govt. doctors?",
  "option1": "Chhattisgarh",
  "option2": "Rajasthan",
  "option3": "Andhra Pradesh",
  "option4": "Odisha",
  "option5": "",
  "answer": "Andhra Pradesh",
  "explanation": "The Andhra Pradesh government has decided to ban private practice by doctors working in government hospitals and increase their salaries as compensation in accordance with the recommendations made by the experts committee on reforms in the health sector headed by former Union Health Secretary K. Sujatha Rao. This is the second time that government doctors are being barred from private practice in Andhra Pradesh. Private practice by government doctors was banned in undivided Andhra in April 1993 by the then Chief Minister N.T. Rama Rao."
}