{
  "created_at": "2018-01-20T20:58:32.000Z",
  "updated_at": "2021-01-06T08:24:15.848Z",
  "id": "9b873a4e-34d8-4547-b365-ada5dbb94ce9",
  "labels": "current-affairs,2018-01-21",
  "question": "If the people prefer to keep cash with them rather than deposits, which among the following impacts will be seen on the Money Supply of the country?",
  "option1": "The money supply of the country will increase",
  "option2": "The money supply of the country will decrease",
  "option3": "The money supply of the country will not change",
  "option4": "The money supply of the country may increase or decrease",
  "option5": "",
  "answer": "The money supply of the country will decrease",
  "explanation": ""
}