{
  "created_at": "2021-01-09T03:43:10.984Z",
  "updated_at": "2021-01-09T03:43:10.984Z",
  "id": "5fe2ad84-4f3f-4128-9c70-c2781f0da4f1",
  "labels": "general-knowledge,books-and-authors",
  "question": "George Bernard Shaw, the great dramatist, was",
  "option1": "a Welsh",
  "option2": "an Irishman",
  "option3": "a Soctsman",
  "option4": "an Englishman",
  "option5": "",
  "answer": "an Irishman",
  "explanation": "No answer description available for this question. Let us discuss.",
  "verified_at": ""
}