{
  "created_at": "2017-06-05T00:00:00.000Z",
  "updated_at": "2021-01-09T09:21:47.451Z",
  "id": "655db8c5-fae2-4598-b514-14910075ac51",
  "labels": "current-affairs,2017-06-05",
  "question": "India launched the first bicycle share scheme in ____________.",
  "option1": "Mysore",
  "option2": "Bangalore",
  "option3": "Chennai",
  "option4": "Hyderabad",
  "option5": "",
  "answer": "Mysore",
  "explanation": "India's first bike sharing scheme launched this weekend in the southern city of Mysuru. The bikes, of which 450 will be available to the city's 1.2 million inhabitants, will be hirable from 48 docking stations across the city. The scheme, which is being run by bike sharing company Trin Trin, was launched with a fair amount of fanfare in the city of Mysuru which is already known as India's cleanest city.",
  "verified_at": ""
}