{
  "created_at": "2017-12-06T00:22:56.000Z",
  "updated_at": "2021-01-06T08:24:11.289Z",
  "id": "59982a21-cba1-4fca-a2b6-b5dad7c75479",
  "labels": "current-affairs,2017-12-07",
  "question": "What is the theme of the 2017 World Soil Day (WSD)?",
  "option1": "Soil day for future life",
  "option2": "Soils & Pulses: Symbiosis for life",
  "option3": "Healthy soils for a healthy life",
  "option4": "Caring for the Planet starts from the Ground",
  "option5": "",
  "answer": "Caring for the Planet starts from the Ground",
  "explanation": "The World Soil Day (WSD) is observed every year on December 5 to communicate messages on the importance of soil quality for food security, healthy ecosystems and human well-being. The 2017 theme is “Caring for the Planet starts from the Ground”. It is celebrated annually at the Food and Agriculture Organization (FAO) headquarters in Rome, the regional offices and through national and local events."
}