{
  "created_at": "2020-05-30T17:18:41.000Z",
  "updated_at": "2021-01-06T08:24:55.101Z",
  "id": "6197f38a-b1af-44ba-89cb-fc4caff60803",
  "labels": "current-affairs,2020-05-31",
  "question": "Which sector does a pink collar worker belong to?",
  "option1": "Primary",
  "option2": "Quinary",
  "option3": "Tertiary",
  "option4": "Secondary",
  "option5": "",
  "answer": "Tertiary",
  "explanation": "The pink-collar worker is one who is employed in a job that is traditionally considered to be women\\'s work.<br />The term pink-collar worker was used to distinguish female-orientated jobs from the others. They are part of the tertiary sector."
}