{
  "created_at": "2018-08-03T21:06:55.000Z",
  "updated_at": "2021-01-06T08:24:32.579Z",
  "id": "378e8eb5-8028-4369-a471-9fcc479c32bc",
  "labels": "current-affairs,2018-08-04",
  "question": "Consider the following statements about the Athens Declaration of 2016: <ol> <li>The meet aims at protecting pollution from maritime transport</li> <li>The Athens meet is the first to adopt the 2030 Agenda and the Paris Climate Agreement</li> </ol> Which of the above statements is/are correct?",
  "option1": "Only 1",
  "option2": "Only 2",
  "option3": "Both 1 & 2",
  "option4": "Neither 1 nor 2",
  "option5": "",
  "answer": "Both 1 & 2",
  "explanation": "Recently, the Athens meet was held by a group consisting of 21 Mediterranean countries. It aimed at Protection of the Marine Environment and the Coastal Region from maritime transport, marine exploration and land based activities; protecting biodiversity; managing coastal zones; and increasing the reluctance of Mediterranean Sea to the impacts of climate Change. The Athens meet is one of the first to follow the adoption of the 2030 Agenda and the Paris Climate Agreement.<br>"
}