{
  "created_at": "2017-02-11T00:00:00.000Z",
  "updated_at": "2021-01-09T09:16:29.690Z",
  "id": "7702c2e8-374a-461a-84ff-10b09c19ed7a",
  "labels": "current-affairs,2017-02-11",
  "question": "Which Indian Institute of Technology (IIT) to set up India's first school on Quality and Reliability (Q&R)?",
  "option1": "IIT Bombay",
  "option2": "IIT Indore",
  "option3": "IIT Kharagpur",
  "option4": "IIT Madras",
  "option5": "",
  "answer": "IIT Kharagpur",
  "explanation": "No answer description available for this question. Let us discuss.",
  "verified_at": ""
}