{
  "created_at": "2018-08-03T20:52:30.000Z",
  "updated_at": "2021-01-06T08:24:30.120Z",
  "id": "76e1bd5c-b2ff-40bd-87bd-ab8273206c39",
  "labels": "current-affairs,2018-08-04",
  "question": "What is known as &#8216;Aman&#8217; in West Bengal, &#8216;Sali&#8217; in Assam, &#8216;Sarrad&#8217; in Orissa, &#8216;Agahani&#8217; in Bihar and Uttar Pradesh?",
  "option1": "Guavas",
  "option2": "Winter rice",
  "option3": "Pulses",
  "option4": "Castor oil seed",
  "option5": "",
  "answer": "Winter rice",
  "explanation": "The main rice growing season in the country is the &#8216;Kharif&#8217;. It is known as winter rice as per the harvesting time. The sowing time of winter (Kharif) rice is June-July and it is harvested in November-December. Winter rice is known as &#8216;Aman&#8217; in West Bengal, &#8216;Sali&#8217; in Assam, &#8216;Sarrad&#8217; in Orissa, &#8216;Agahani&#8217; in Bihar and Uttar Pradesh, &#8216;Sarava&#8217; in Andhra Pradesh, &#8216;Mundakan&#8217; in Kerala and &#8216;Samba/Thaladi&#8217; in Tamil Nadu. About 84% of the country&#8217;s rice crop is grown in this season and generally, medium to long duration varieties are grown in this season."
}