{
  "created_at": "2021-01-09T03:42:49.625Z",
  "updated_at": "2021-01-09T03:42:49.625Z",
  "id": "dfcf54ca-6e2a-442f-bfa9-1b8ccf82c0f4",
  "labels": "general-knowledge,inventions",
  "question": "What invention by Garnet Carter made its debut at the Fairyland Inn Resort in Lookout Mountain, Tennessee, in 1927?",
  "option1": "Miniature golf",
  "option2": "Swimming pool slide",
  "option3": "Ski lift",
  "option4": "Golf cart",
  "option5": "",
  "answer": "Miniature golf",
  "explanation": "It was originally called 'Tom Thumb Golf'.",
  "verified_at": ""
}