{
  "created_at": "2019-12-23T21:59:44.000Z",
  "updated_at": "2021-01-06T08:24:47.333Z",
  "id": "111a06e3-cba6-4ebf-81b3-4726b8507c01",
  "labels": "current-affairs,2019-12-24",
  "question": "The Trak Island has been in news recently. In this context, consider the following statements:<br />\n<ol>\n<li>It is located in the Bay of Bengal.</li>\n<li>BrahMos surface-to-surface missiles were tested here.</li>\n</ol>\nWhich of the above statements is/are true?",
  "option1": "Only 1 is correct",
  "option2": "Only 2 is correct",
  "option3": "Neither 1 nor 2 is correct",
  "option4": "Both 1 and  2 are correct",
  "option5": "",
  "answer": "Both 1 and  2 are correct",
  "explanation": "<strong>Statement 1 is correct:</strong>\nThe Trak Island is located in the Bay of Bengal. It is a part of the Andaman and Nicobar group of islands. It is located in the Nicobar group of islands, north of the Little Nicobar Island. It belongs to the Southern Group known as the Sambelong.\n <strong>Statement 2 is correct:</strong>\nTwo BrahMos surface to surface missiles were tested at the Trak Island in October. It is a part of routine operational training. The missiles successfully hit the target. The targets were set at 300km distance and was tested by the Indian Air Force.\n&nbsp;"
}