{
  "created_at": "2017-03-01T23:32:44.000Z",
  "updated_at": "2021-01-06T08:24:08.793Z",
  "id": "2a9942c3-d868-47b3-a22d-69414472d0f0",
  "labels": "current-affairs,2017-03-02",
  "question": "Who has been named as the \"Captain of the Year\" at 2017 ESPNcricinfo Awards?",
  "option1": "Virat Kohli",
  "option2": "Ben Stokes",
  "option3": "Faf du Plessis",
  "option4": "Steven Smith",
  "option5": "",
  "answer": "Virat Kohli",
  "explanation": "Indian Test skipper Virat Kohli has been named as the ‘Captain of the Year’ at the 10th annual ESPNcricinfo Awards. Kohli led India to 9 wins out of 12 Tests in the year gone-by. Apart from this, Englishman Ben Stokes won the Test Batting Performance of the Year for his incredible counterattacking innings of 258 runs off 198 balls against South Africa in Cape Town."
}