{
  "created_at": "2017-07-11T00:00:00.000Z",
  "updated_at": "2021-01-09T09:23:14.713Z",
  "id": "c3222360-1fa1-4403-8a87-16365194ce32",
  "labels": "current-affairs,2017-07-11",
  "question": "In which month the Union Government decided to organise global food fair to boost the Food sector?",
  "option1": "November",
  "option2": "October",
  "option3": "August",
  "option4": "September",
  "option5": "",
  "answer": "November",
  "explanation": "The Union Government of India will organize a global food fair in November this year to provide a platform to Indian farmers and manufacturers to showcase their products and explore partnerships with foreign companies. The three-day international level fair 'World Food India 2017 is being organized on November 3-5 by the Food Processing Ministry.",
  "verified_at": ""
}