{
  "created_at": "2020-12-07T18:52:46.000Z",
  "updated_at": "2021-01-06T08:25:13.110Z",
  "id": "3cf07e8d-bc5c-44bc-8dd8-91543f497046",
  "labels": "current-affairs,2020-12-08",
  "question": "Which Amendment Act enabled the president to limit the operation of a National Emergency to a specified part of India?",
  "option1": "32nd Amendment Act",
  "option2": "38th Amendment Act",
  "option3": "42nd Amendment Act",
  "option4": "44th Amendment Act",
  "option5": "",
  "answer": "42nd Amendment Act",
  "explanation": "The 42nd Amendment Act of 1976 enabled the president to limit the operation of a National Emergency to a specified part of India."
}