{
  "created_at": "2020-07-09T19:17:02.000Z",
  "updated_at": "2021-01-06T08:25:00.110Z",
  "id": "d8606d08-4396-42d5-92b2-be5606d4c8f3",
  "labels": "current-affairs,2020-07-10",
  "question": "From which nation Botswana got its independence in 1966?",
  "option1": "France",
  "option2": "Portugal",
  "option3": "United Kingdom",
  "option4": "Spain",
  "option5": "",
  "answer": "United Kingdom",
  "explanation": "Botswana got its independence in 1966 from the United Kingdom. The Berlin Conference of 1885 allowed Great Britain to annex Botswana. Botswana was known as the British protectorate of Bechuanaland. In 1964, the British allowed democratic self-government in Botswana, which finally lead to its independence in 1966."
}