{
  "created_at": "2018-03-19T23:03:58.000Z",
  "updated_at": "2021-01-06T08:24:21.596Z",
  "id": "24800d7b-2a0e-43fb-8f4f-2ccdb17ef9ae",
  "labels": "current-affairs,2018-03-20",
  "question": "Didda, the famous queen of Kashmir belong to which dynasty?",
  "option1": "Lohara",
  "option2": "Utpal",
  "option3": "Chandella",
  "option4": "Karkot",
  "option5": "",
  "answer": "Lohara",
  "explanation": "Didda was the Lohara dynasty princess who married to the king of Kashmir \\'Ksemagupta\\' and united the kingdom of Lohara  with that of her husband. After the death of her husband, she ruled Kashmir from 958 AD to 1003 AD ."
}