{
  "created_at": "2019-02-05T12:08:03.000Z",
  "updated_at": "2021-01-06T08:24:36.633Z",
  "id": "2c438603-ac63-40cc-8808-4979ac59634e",
  "labels": "current-affairs,2019-02-06",
  "question": "Choose the incorrect statement:",
  "option1": "Slaked lime is also known as Calcium hydroxide",
  "option2": "Suspension of slaked lime is known as Milk of lime",
  "option3": "Aqueous solution of slaked lime is known as quick lime",
  "option4": "Both a and b",
  "option5": "",
  "answer": "Aqueous solution of slaked lime is known as quick lime",
  "explanation": "Calcium hydroxide(Slaked lime) is prepared by adding water to quick lime, CaO. Suspension of slaked lime is known as Milk of lime and aqueous solution of slaked lime is known as lime water."
}