{
  "created_at": "2020-07-05T17:42:36.000Z",
  "updated_at": "2021-01-06T08:24:58.553Z",
  "id": "017964d3-97f4-402e-be49-41751e9c4de1",
  "labels": "current-affairs,2020-07-06",
  "question": "Which among the following matches of rivers and their tributaries are correct?<br />1. Krishna- Bhima</span><br />2. Brahamaputra- Tista</span><br />3. Godavari- Indravati<br />4. Yamuna- ChambalChoose the correct option from the codes given below :</span>",
  "option1": "1 & 2",
  "option2": "1, 2 & 3",
  "option3": "1, 3 & 4",
  "option4": "1, 2, 3 & 4",
  "option5": "",
  "answer": "1, 2, 3 & 4",
  "explanation": "Krishna – Bhima River is a major river in South India. It flows through Maharashtra, Karnataka, and Telangana states, before entering into the Krishna River.<br />Brahmaputra – Teesta River originates in the Himalayas and flows through Sikkim and West Bengal before entering Bangladesh, where it flows into the Brahmaputra.<br />Godavari – Indravati River This river is a stream of the river Godavari. Its starting point is found to be the Ghats of Dandakaranya range from a hilltop village Mardiguda of Odisha.<br />Yamuna – Chambal River is a tributary of the Yamuna River in central India. The river flows through Madhya Pradesh, Rajasthan and created a boundary between Rajasthan and Madhya Pradesh before joining the Yamuna in Uttar Pradesh.</span>"
}