{
  "created_at": "2019-12-23T21:59:45.000Z",
  "updated_at": "2021-01-06T08:24:47.333Z",
  "id": "52eafba8-acbc-4375-863c-c30b163824f3",
  "labels": "current-affairs,2019-12-24",
  "question": "The Aye-aye has been in news recently. In this context, consider the following statements:<br />\n<ol>\n<li>It is the only mammal with a sixth digit.</li>\n<li>It is found in Madagascar.</li>\n</ol>\nWhich of the above statements is/are correct?",
  "option1": "Only 1 is correct",
  "option2": "Only 2 is correct",
  "option3": "Neither 1 nor 2 is correct",
  "option4": "Both 1 and 2 are correct",
  "option5": "",
  "answer": "Only 2 is correct",
  "explanation": "<strong>Statement 1 is incorrect:</strong>\nApart from the aye-aye, the Giant Panda is another mammal that has the sixth digit. The aye-aye uses the sixth digit to improve its grip. This digit is called a pseudo-thumb. It can move the digit in 3 directions and has bone and cartilage in it.\n<strong>Statement 2 is correct:</strong>\nThe aye-aye is a lemur found in the island of Madagascar, especially along its eastern coast. It is an endangered species. It is the largest nocturnal primate. It is known for its pseudo-digit and its perpetually growing teeth. It is an arboreal animal."
}