{
  "created_at": "2020-07-25T22:50:11.000Z",
  "updated_at": "2021-01-06T08:25:02.925Z",
  "id": "57037f81-00bf-4c66-bfdf-c96ce25c47f1",
  "labels": "current-affairs,2020-07-26",
  "question": "When was Jana Gana Mana adopted as the national anthem of India?",
  "option1": "1950-01-23T18:30:00.000Z",
  "option2": "1950-01-25T18:30:00.000Z",
  "option3": "1947-08-14T18:30:00.000Z",
  "option4": "1949-11-25T18:30:00.000Z",
  "option5": "",
  "answer": "1950-01-23T18:30:00.000Z",
  "explanation": "The Constituent Assembly adopted Jana Gana Mana, composed by Rabindranath Tagore, as the national anthem of India on the 24th January, 1950."
}