{
  "created_at": "2020-08-15T03:46:11.000Z",
  "updated_at": "2021-01-06T08:25:05.781Z",
  "id": "1b774741-8a3b-4a68-8046-135483d69925",
  "labels": "current-affairs,2020-08-16",
  "question": "An Ayurveda based bio degradable face mask named “Pavitrapati” is developed by which organisation?",
  "option1": "Defence Research Development Organisation",
  "option2": "Indian Space Research Organisation",
  "option3": "Defence Institute of Advanced Technology",
  "option4": "Hindustan Aeronautics Limited",
  "option5": "",
  "answer": "Defence Institute of Advanced Technology",
  "explanation": "An Ayurveda Based Biodegradable Face Mask named “Pavitrapati” has been developed by Defence Institute of Advanced Technology, (DIAT) Pune. <br />In this regard, an agreement was signed between DIAT Pune and a private company for mass development of the product. The company has now offered the face mask for sale. Similarly, the technology of developing anti-microbial body suit named “Aushada tara” is also transferred to the company."
}