{
  "created_at": "2020-04-22T04:37:51.000Z",
  "updated_at": "2021-01-06T08:24:52.543Z",
  "id": "35917798-4296-4c12-8595-07050e2b6d52",
  "labels": "current-affairs,2020-04-23",
  "question": "Every year, April 21 is celebrated as Civil Services Day, to commemorate the address of which Indian leader, made among the probationers of Administrative Services Officers in 1947?",
  "option1": "Jawaharlal Nehru",
  "option2": "B.R.Ambedkar",
  "option3": "Sardar Vallabhbhai Patel",
  "option4": "Lal Bahadur Shastri",
  "option5": "",
  "answer": "Sardar Vallabhbhai Patel",
  "explanation": "On April 21, 1947 the first Home Minister of India Sardar Vallabhbhai Patel addressed the probationers of Administrative Services Officers in 1947.\r\nWhile delivering the historical address at the Metcalf House, Delhi, he described the Civil servants as ‘steel frame of India’. To commemorate this occasion, April 21 has been observed as the Civil Services Day every year, across the country."
}