{
  "created_at": "2018-02-22T18:51:41.000Z",
  "updated_at": "2021-01-06T08:24:19.325Z",
  "id": "83245278-ff75-4710-930f-70d6a8df13e2",
  "labels": "current-affairs,2018-02-23",
  "question": "Which of the following is the smallest wildllife sanctuary in Himachal pradesh?",
  "option1": "Talra",
  "option2": "Shilli",
  "option3": "Shikari Devi",
  "option4": "Tirthan",
  "option5": "",
  "answer": "Shilli",
  "explanation": "Shilli wildlife sanctuary located in Solan district is the smallest wildllife sanctuary in Himachal pradesh"
}