{
  "created_at": "2017-03-23T00:00:00.000Z",
  "updated_at": "2021-01-09T09:18:02.718Z",
  "id": "abffb900-9f58-4e17-a57d-38c1b6012180",
  "labels": "current-affairs,2017-03-23",
  "question": "What was the theme of World Meteorological Day 2017?",
  "option1": "Climate Change",
  "option2": "Disaster Risk Management",
  "option3": "Understanding Clouds",
  "option4": "Our future climate",
  "option5": "",
  "answer": "Understanding Clouds",
  "explanation": "No answer description available for this question. Let us discuss.",
  "verified_at": ""
}