{
  "created_at": "2018-08-21T22:21:14.000Z",
  "updated_at": "2021-01-06T08:24:33.880Z",
  "id": "6409b9fe-2202-448a-a0fb-5441d6f85174",
  "labels": "current-affairs,2018-08-22",
  "question": "Recently tested  Anti-Tank Guided Missile ‘Helina' is helicopter-launched version of which missile?",
  "option1": "Akash",
  "option2": "Nag",
  "option3": "Prithvi",
  "option4": "Agni",
  "option5": "",
  "answer": "Nag",
  "explanation": "On August 19, India has successfully test-fired the indigenously developed helicopter launched Anti-Tank Guided Missile (ATGM) ‘HELINA’  from an Army helicopter \\'Rudra\\' in Pokhran test range in Rajasthan. The HELINA weapon system tested for its full range was released smoothly from the launch platform. The missile hit the target with high precision. The missile is guided by an Infrared Imaging Seeker (IIR) operating in the Lock-on-Before-Launch mode. It is one of the most advanced anti-tank weapons in the world. It is the helicopter-launched version of NAG and has a hit range of 7-8 km. The production and induction of the missile are likely to happen in 2019. Beside this, the indigenously designed and developed guided bombs Smart Anti Airfield Weapon (SAAW) also successfully flight tested from IAF aircraft at Chandan range in Jaisalmer. The SAAW is the combined effort of the DRDO, IAF and HAL. This weapon is capable of destroying a variety of ground targets using precision navigation."
}