{
  "created_at": "2020-10-06T04:55:57.000Z",
  "updated_at": "2021-01-06T08:25:10.525Z",
  "id": "264772e8-a62a-42f7-9bc4-3e4721d5a413",
  "labels": "current-affairs,2020-10-07",
  "question": "The Union Government has paid over Rs. 1000 crore to around 40000 farmers for procurement of which food grain?",
  "option1": "Wheat",
  "option2": "Rice",
  "option3": "Maize",
  "option4": "Sorghum",
  "option5": "",
  "answer": "Rice",
  "explanation": "<div>The Central Government has paid around Rs. 1082 crore were paid to over 41 thousand farmers for procurement of paddy on Minimum Support Price.</div>\r\n<div>As per the Consumer Affairs Ministry, as on October 10, the cumulative procurement of Paddy in this Kharif Marketing Season is over 5.73 lakh tonnes. Paddy procurement for the 2020-21 year has also commenced across the procuring States.</div>\r\n<div> </div>"
}