{
  "created_at": "2020-07-12T11:02:22.000Z",
  "updated_at": "2021-01-06T08:25:00.110Z",
  "id": "def1b275-0edb-4bc0-a35f-428bd3b862f7",
  "labels": "current-affairs,2020-07-13",
  "question": "Which of the following statements are correct about the Mandu architecture?<br />1) Use of lofty plinth.<br />2) Structures are relatively smaller in height.<br />3) Largescale use of colored and glazed tiles.<br />Select the correct option from the codes given below:",
  "option1": "Only 1 & 2",
  "option2": "Only 2 & 3",
  "option3": "Only 1 & 3",
  "option4": "1, 2, & 3",
  "option5": "",
  "answer": "Only 1 & 3",
  "explanation": "The Mandu architecture was different from the Gujarat style of architecture. They were massive due to the use of lofty plinth for the buildings and there was largescale use of coloured and glazed tiles which provided variety to the buildings."
}