{
  "created_at": "2019-02-11T22:48:06.000Z",
  "updated_at": "2021-01-06T08:24:36.633Z",
  "id": "747dd855-8ec5-4d1a-9d89-9f0bcb4dd6ab",
  "labels": "current-affairs,2019-02-12",
  "question": "Which city is the venue of the 2nd ASEAN-India Youth Summit 2019?",
  "option1": "Pune",
  "option2": "Hyderabad",
  "option3": "Guwahati",
  "option4": "Jaipur",
  "option5": "",
  "answer": "Guwahati",
  "explanation": "The 2nd ASEAN-India Youth Summit 2019 was held in Guwahati, Assam on the theme “Connectivity is the pathway to shared prosperity” from 03-06 February 2019. It is organized by India Foundation in collaboration with Union Ministry of External Affairs (MEA) and Government of Assam. Over 100 youth delegates the ten ASEAN countries - Brunei, Cambodia, Indonesia, Lao PDR, Malaysia, Myanmar, Philippines, Singapore, Thailand, and Vietnam took part in the summit. The purpose of the summit was to strengthen the mutual cooperation among the youth leaders from India and the ASEAN countries. Hence, the 2019 summit is a step to facilitate Socio-cultural exchanges between the countries to further strengthen the values of tolerance, pluralism and diversity."
}