{
  "created_at": "2020-07-14T14:19:19.000Z",
  "updated_at": "2021-01-06T08:25:01.106Z",
  "id": "c85cdfdc-8f3c-4b9b-9fab-681371ab4d79",
  "labels": "current-affairs,2020-07-15",
  "question": "Which of the following statements are correct with respect to the penetration of English into Bengal?<br />1. Job Charnock arrived in Sutanati in August 1690.<br />2. Job Charnock laid the foundation of Calcutta which later became the heart of the British Indian Empire.<br />3.The French East India Company built a fort near the Fort William in Calcutta.<br />Select the correct answer using the code given below:",
  "option1": "Only 1",
  "option2": "Only 1 & 2",
  "option3": "Only 2 & 3",
  "option4": "1, 2 & 3",
  "option5": "",
  "answer": "Only 1 & 2",
  "explanation": "Job Charnock arrived in Sutanati in August 1690. Job Charnock, an administrator with the British East India Company is traditionally credited with the honour of founding the city of Calcutta. Fort William was established to protect the East India Company’s trade in the city of Calcutta, the principal town of the Bengal Presidency."
}