{
  "created_at": "2018-08-03T20:59:54.000Z",
  "updated_at": "2021-01-06T08:24:30.854Z",
  "id": "a543bb38-1324-4194-8c5a-7d7d2a8feb31",
  "labels": "current-affairs,2018-08-04",
  "question": "Which of the following statements is correct about the Rashtriya Madhyamik Shiksha Abhiyan (RMSA)? <ol> <li>It is a centrally sponsored scheme of “vocationalisation” of secondary and higher secondary education.</li> <li>The scheme is being implemented by the State government societies established for implementation of the scheme.</li> </ol> Which of the above statements is/are correct?",
  "option1": "Only 1",
  "option2": "Only 2",
  "option3": "Both 1 & 2",
  "option4": "Neither 1 nor 2",
  "option5": "",
  "answer": "Both 1 & 2",
  "explanation": "Both are correct statements Rashtriya Madhyamik Shiksha Abhiyan (RMSA) is a centrally sponsored scheme of vocationalisation of secondary and higher education in the country. It focuses on enhancing the employability of youth through demand-driven, competency-based, modular vocational courses, while reducing drop-out rates. The major objective of the scheme is to enhance access and improve quality of education at the secondary stage while ensuring equity. The umbrella scheme of RMSA will be implemented at state level by RMSA societies established particularly for this work."
}