{
  "created_at": "2018-08-03T20:39:20.000Z",
  "updated_at": "2021-01-06T08:24:27.497Z",
  "id": "64d4c29b-3f66-4ba8-ae12-1bb039065d9f",
  "labels": "current-affairs,2018-08-04",
  "question": "&nbsp; &nbsp; &nbsp;Consider the following pairs: <ol> <li>Bones of Camel -  Kalibangan</li> <li>Houses with doors on the main streets -  Lothal</li> <li>Largest burial site of Indus Valley Civilization -  Farmana</li> </ol> &nbsp; &nbsp; Which of the above is/are correct?",
  "option1": "1 & 2 Only",
  "option2": "2 Only",
  "option3": "2 & 3 Only",
  "option4": "1, 2 & 3",
  "option5": "",
  "answer": "1, 2 & 3",
  "explanation": "Farmana Khas&nbsp;or&nbsp;Daksh Khera is an archaeological site in Rohtak district of Haryana. It is the largest burial site of IVC, with 65 burials, found in India. Evidence of Houses with doors on the main streets has been found at Lothal. Bones of camel were found at Kalibangan."
}