{
  "created_at": "2018-03-17T23:33:03.000Z",
  "updated_at": "2021-01-06T08:24:21.596Z",
  "id": "ce34f767-0251-4867-b268-c58dd3d1f930",
  "labels": "current-affairs,2018-03-18",
  "question": "Which Indian para-athlete has recently secured the No. 1 rank in Asia in F53 Javelin category?",
  "option1": "Rinku Hooda",
  "option2": "Deepa Malik",
  "option3": "Karamjyoti Dalal",
  "option4": "Pooja Khanna",
  "option5": "",
  "answer": "Deepa Malik",
  "explanation": "Indian para-athlete Deepa Malik has won a gold medal in the F-53/54 category javelin event at the World Para Athletics Grand Prix in Dubai on March 15, 2018. With this, she has secured the No. 1 rank in Asia in F53 Javelin category. With the win, Deepa has also qualified for the 2018 Asian Para Games, which is scheduled to be held in Jakarta, Indonesia from October 8-16. With that she qualified for the 2018 Asian Para Games, which is scheduled to be held in Jakarta, Indonesia from October 8-16. Beside this, Malik is the first Indian woman to win a medal in Paralympic Games and won a Silver medal at the 2016 Summer Paralympics in the shot put. She has been honoured with the Arjuna award in 2012 and has also been conferred the prestigious Padma Shri award in 2017 for her achievements."
}