{
  "created_at": "2019-08-17T16:49:59.000Z",
  "updated_at": "2021-01-06T08:24:42.151Z",
  "id": "8e149c9f-7525-4357-b78a-f3dea63ab8e5",
  "labels": "current-affairs,2019-08-18",
  "question": "Why Gandhiji did started the Dandi March?",
  "option1": "To demonstrate against the policies of British empire",
  "option2": "To break the salt law",
  "option3": "To boycott foreign goods",
  "option4": "None of the above",
  "option5": "",
  "answer": "To break the salt law",
  "explanation": "On 12th March 1930, Mahatma Gandhi started a march from Sabarmati Ashram in Ahmadabad to the sea shore at Dandi. So that is exactly what Gandhi decided to do; pick up salt from the seashore at Dandi and start the Civil Disobedience Satyagraha which was a protest against the policies of British empire. The march began on 12th March and ended on 5th April, 1930."
}