{
  "created_at": "2020-05-02T20:58:37.000Z",
  "updated_at": "2021-01-06T08:24:53.699Z",
  "id": "70ae9201-f1b4-494d-b829-e277cadf04fc",
  "labels": "current-affairs,2020-05-03",
  "question": "The Punjab Land Alienation Act was passed in which year?",
  "option1": 1900,
  "option2": 1903,
  "option3": 1905,
  "option4": 1909,
  "option5": "",
  "answer": 1900,
  "explanation": "In the year 1900, the Punjab Land Alienation Act was passed during the viceroyship of Lord Curzon. Its main aim was to limit the transfer the ownership of land in Punjab province. A category named \\\"agricultural tribes\\\" was created.</span>"
}