{
  "created_at": "2021-02-19T07:39:08.000Z",
  "updated_at": "2021-02-19T07:39:08.000Z",
  "id": "2cae1e9b-5676-42ff-a20b-bf0a320a355e",
  "labels": "current-affairs,2021-02-20",
  "question": "What was \"John von Neumann\" famous for?",
  "option1": "As a Danish-American polymath",
  "option2": "As a Hungarian-American polymath",
  "option3": "As a German-American polymath",
  "option4": "As a Polish-American polymath",
  "option5": "",
  "answer": "As a Hungarian-American polymath",
  "explanation": "John von Neumann was a Hungarian-American mathematician, physicist, computer scientist, engineer and polymath. Von Neumann was generally regarded as the foremost mathematician of his time and said to be \"the last representative of the great mathematicians\". He integrated pure and applied sciences.",
  "verified_at": ""
}