{
  "created_at": "2019-08-14T21:16:39.000Z",
  "updated_at": "2021-01-06T08:24:42.151Z",
  "id": "3a0a1d9f-8821-4db2-bca4-4220a8632d29",
  "labels": "current-affairs,2019-08-15",
  "question": "As per Pradhan Mantri Kisan Maan-Dhan Yojana (PM-KMY), a monthly pension of how much amount will be provided to eligible farmers on attaining the age of 60?",
  "option1": "Rs 5000",
  "option2": "Rs 6000",
  "option3": "Rs 3000",
  "option4": "Rs 4000",
  "option5": "",
  "answer": "Rs 3000",
  "explanation": "The Union Government has recently started registration for the Pradhan Mantri Kisan Maan-Dhan Yojana (PM-KMY) with an aim to improve the life of Small and Marginal Farmers of the country.  This scheme for farmers has been announced in the Union Budget 2019-20. The scheme is voluntary and contributory for farmers in the entry age group of 18 to 40 years and a monthly pension of Rs. 3000/- will be provided to them on attaining the age of 60 years. The farmers will have to make a monthly contribution of Rs.55 to Rs.200, depending on their age of entry, in the Pension Fund till they reach the retirement date i.e. the age of 60 years. The Central Government will also make an equal contribution of the same amount in the pension fund. The spouse is also eligible to get a separate pension of Rs.3000/- upon making separate contributions to the Fund. The Life Insurance Corporation of India (LIC) shall be the Pension Fund Manager and responsible for Pension pay out. The PM-KMY will be implemented across the country, including Jammu and Kashmir and Ladakh."
}