{
  "created_at": "2020-03-14T17:42:35.000Z",
  "updated_at": "2021-01-06T08:24:50.637Z",
  "id": "9611dc18-e275-4c69-9215-6a4ddb75f790",
  "labels": "current-affairs,2020-03-15",
  "question": "Odisha Mining Corporation Limited was designated with which of the following?",
  "option1": "Gold Category State PSU",
  "option2": "Silver Category State PSU",
  "option3": "Navaratna",
  "option4": "Maharatna",
  "option5": "",
  "answer": "Gold Category State PSU",
  "explanation": "Odisha Mining Corporation Limited was designated with  Gold Category State PSU in the year 2012."
}