{
  "created_at": "2020-09-19T17:20:11.000Z",
  "updated_at": "2021-01-06T08:25:09.400Z",
  "id": "751e75fe-06b8-427f-8e6c-334407abdeae",
  "labels": "current-affairs,2020-09-20",
  "question": "Which of the following territories celebrates the \"Saint-Georges International Music Festival\"?",
  "option1": "Antigua and Barbuda",
  "option2": "Dominica",
  "option3": "The Bahamas",
  "option4": "Guadeloupe",
  "option5": "",
  "answer": "Guadeloupe",
  "explanation": "The Saint-Georges International Music Festival is a prominent music festival held in Guadeloupe, an overseas territory of France which celebrates the life and work of Joseph Bologne, Le Chevalier de Saint-Georges. This festival become one of the largest classical music festivals in the Caribbean."
}