{
  "created_at": "2020-07-25T18:32:05.000Z",
  "updated_at": "2021-01-06T08:25:02.082Z",
  "id": "ce443683-8161-478d-a978-257721df797e",
  "labels": "current-affairs,2020-07-26",
  "question": "Vidya Bal, who recently passed away, was associated with which of the following field?",
  "option1": "Social Activist",
  "option2": "Classical Dancer",
  "option3": "Actress",
  "option4": "Director of DGCA",
  "option5": "",
  "answer": "Social Activist",
  "explanation": "Vidya Bal, who recently passed away, was a famous social activist of Maharashtra. She was born in Pune. She made her immense contribution to the field of improving the social status of women."
}