{
  "created_at": "2021-01-05T05:57:07.000Z",
  "updated_at": "2021-01-06T08:25:13.847Z",
  "id": "a0af9862-9ff2-447c-a506-c22523503771",
  "labels": "current-affairs,2021-01-06",
  "question": "Which Defence force has proposed to acquire 12 high-performance patrol boats?",
  "option1": "Indian Navy",
  "option2": "Indian Coast Guard",
  "option3": "Indian Air Force",
  "option4": "Indian Army",
  "option5": "",
  "answer": "Indian Army",
  "explanation": "The Indian Army has signed a deal with the state-run Goa Shipyard Ltd., for procurement of 12 high performance patrol boats. <br />This is aimed to secure and perform surveillance of large lakes like the Pangong lake in Ladakh. This comes in back drop of the tussle between the Indian Army and the Chinese counterpart at the eastern Ladakh."
}