{
  "created_at": "2019-01-19T22:14:09.000Z",
  "updated_at": "2021-01-06T08:24:35.506Z",
  "id": "25ff8851-88cd-405a-a5f6-d6ef947d4192",
  "labels": "current-affairs,2019-01-20",
  "question": "Which of the following state governments have approved 10% reservation reservation for poor among general category?",
  "option1": "Odisha and Uttar Pradesh",
  "option2": "Gujarat and Assam",
  "option3": "Chhattisgarh and Rajasthan",
  "option4": "Jharkhand and Uttar Pradesh",
  "option5": "",
  "answer": "Jharkhand and Uttar Pradesh",
  "explanation": "After Gujarat and Jharkhand, the Uttar Pradesh government has approved 10% reservation in jobs and educational institutions for economically backward in the general category. The decision was taken at the state cabinet meeting chaired by Chief Minister Yogi Adityanath in Lucknow. Recently, President Ram Nath Kovind cleared the landmark Constitution (124 Amendment) Bill, 2019 passed by parliament, which will provide 10% reservation in government jobs and college seats for people outside high income brackets. Now, the Act empowers all individuals of the General category whose family’s combined annual income is less than Rs 8 lakh, and who hold less than five acres of agricultural land."
}