{
  "created_at": "2021-01-31T10:50:18.000Z",
  "updated_at": "2021-01-31T10:50:18.000Z",
  "id": "c5b7130f-5262-4ba5-93bd-3127c2b9152e",
  "labels": "current-affairs,2021-02-01",
  "question": "Which country is the largest producer of gold in the African continent?",
  "option1": "Ghana",
  "option2": "South Africa",
  "option3": "Kenya",
  "option4": "Zimbabwe",
  "option5": "",
  "answer": "Ghana",
  "explanation": "Ghana is Africa’s largest producer of gold, beating out South Africa for the top spot in 2019, and is also known for its reserves of various industrial minerals.",
  "verified_at": ""
}