{
  "created_at": "2021-03-16T03:41:57.000Z",
  "updated_at": "2021-03-16T03:41:57.000Z",
  "id": "92781583-a0b1-4ab1-8fe7-2cfd6cc4e3ab",
  "labels": "current-affairs,2021-03-17",
  "question": "All India Tourist Vehicles Authorization and Permit Rules, will be applicable from which date?",
  "option1": "April 1, 2021",
  "option2": "May 1, 2021",
  "option3": "June 1, 2021",
  "option4": "August 1, 2021",
  "option5": "",
  "answer": "April 1, 2021",
  "explanation": "The Ministry of Road Transport and Highways has announced a new scheme, named ‘All India Tourist Vehicles Authorization and Permit Rules, 2021.\r\nUnder the new set of rules, any tourist vehicle operator may apply for an “All India Tourist Authorization/Permit\" through online mode. After required documents are submitted and fees deposited, it will be issued within 30 days of submission of such applications.",
  "verified_at": ""
}